pypgstac/__init__.py
pypgstac/db.py
pypgstac/hydration.py
pypgstac/load.py
pypgstac/migrate.py
pypgstac/py.typed
pypgstac/pypgstac.py
pypgstac/version.py
pypgstac/migrations/pgstac.0.1.9-0.2.3.sql
pypgstac/migrations/pgstac.0.1.9.sql
pypgstac/migrations/pgstac.0.2.3-0.2.4.sql
pypgstac/migrations/pgstac.0.2.3.sql
pypgstac/migrations/pgstac.0.2.4-0.2.5.sql
pypgstac/migrations/pgstac.0.2.4-0.2.7.sql
pypgstac/migrations/pgstac.0.2.4.sql
pypgstac/migrations/pgstac.0.2.5-0.2.7.sql
pypgstac/migrations/pgstac.0.2.5.sql
pypgstac/migrations/pgstac.0.2.7-0.2.8.sql
pypgstac/migrations/pgstac.0.2.7.sql
pypgstac/migrations/pgstac.0.2.8-0.2.9.sql
pypgstac/migrations/pgstac.0.2.8.sql
pypgstac/migrations/pgstac.0.2.9-0.3.0.sql
pypgstac/migrations/pgstac.0.2.9.sql
pypgstac/migrations/pgstac.0.3.0-0.3.1.sql
pypgstac/migrations/pgstac.0.3.0.sql
pypgstac/migrations/pgstac.0.3.1-0.3.2.sql
pypgstac/migrations/pgstac.0.3.1.sql
pypgstac/migrations/pgstac.0.3.2-0.3.3.sql
pypgstac/migrations/pgstac.0.3.2.sql
pypgstac/migrations/pgstac.0.3.3-0.3.4.sql
pypgstac/migrations/pgstac.0.3.3.sql
pypgstac/migrations/pgstac.0.3.4-0.3.5.sql
pypgstac/migrations/pgstac.0.3.4.sql
pypgstac/migrations/pgstac.0.3.5-0.3.6.sql
pypgstac/migrations/pgstac.0.3.5.sql
pypgstac/migrations/pgstac.0.3.6-0.4.0.sql
pypgstac/migrations/pgstac.0.3.6.sql
pypgstac/migrations/pgstac.0.4.0-0.4.1.sql
pypgstac/migrations/pgstac.0.4.0.sql
pypgstac/migrations/pgstac.0.4.1-0.4.2.sql
pypgstac/migrations/pgstac.0.4.1.sql
pypgstac/migrations/pgstac.0.4.2-0.4.3.sql
pypgstac/migrations/pgstac.0.4.2.sql
pypgstac/migrations/pgstac.0.4.3-0.4.4.sql
pypgstac/migrations/pgstac.0.4.3.sql
pypgstac/migrations/pgstac.0.4.4-0.4.5.sql
pypgstac/migrations/pgstac.0.4.4.sql
pypgstac/migrations/pgstac.0.4.5-0.5.0.sql
pypgstac/migrations/pgstac.0.4.5.sql
pypgstac/migrations/pgstac.0.5.0-0.5.1.sql
pypgstac/migrations/pgstac.0.5.0.sql
pypgstac/migrations/pgstac.0.5.1-0.6.0.sql
pypgstac/migrations/pgstac.0.5.1.sql
pypgstac/migrations/pgstac.0.6.0-0.6.1.sql
pypgstac-0.9.8.dist-info/METADATA
pypgstac-0.9.8.dist-info/WHEEL
pypgstac-0.9.8.dist-info/entry_points.txt
pypgstac-0.9.8.dist-info/RECORD
